mcp_lambda/__init__.py
mcp_lambda/client/__init__.py
mcp_lambda/client/lambda_client.py
mcp_lambda/client/streamable_http_sigv4.py
mcp_lambda/handlers/__init__.py
mcp_lambda/handlers/api_gateway_proxy_event_handler.py
mcp_lambda/handlers/api_gateway_proxy_event_v2_handler.py
mcp_lambda/handlers/bedrock_agent_core_gateway_target_handler.py
mcp_lambda/handlers/lambda_function_url_event_handler.py
mcp_lambda/handlers/request_handler.py
mcp_lambda/handlers/streamable_http_handler.py
mcp_lambda/server_adapter/__init__.py
mcp_lambda/server_adapter/adapter.py
mcp_lambda/server_adapter/stdio_server_adapter_request_handler.py
run_mcp_servers_with_aws_lambda-0.5.8.dist-info/METADATA
run_mcp_servers_with_aws_lambda-0.5.8.dist-info/WHEEL
run_mcp_servers_with_aws_lambda-0.5.8.dist-info/RECORD
